{
  "skills": [
    { "name": "React", "icon": "SiReact" },
    { "name": "TypeScript", "icon": "SiTypescript" },
    { "name": "Tailwind CSS", "icon": "SiTailwindcss" },
    { "name": "Next.js", "icon": "SiNextdotjs" },
    { "name": "Node.js", "icon": "SiNodedotjs" },
    { "name": "Python", "icon": "SiPython" },
    { "name": "Java", "icon": "SiOpenjdk" },
    { "name": "FastAPI", "icon": "SiFastapi" },
    { "name": "PostgreSQL", "icon": "SiPostgresql" },
    { "name": "MongoDB", "icon": "SiMongodb" },
    { "name": "Redis", "icon": "SiRedis" },
    { "name": "Supabase", "icon": "SiSupabase" },
    { "name": "TensorFlow", "icon": "SiTensorflow" },
    { "name": "PyTorch", "icon": "SiPytorch" },
    { "name": "Scikit-learn", "icon": "SiScikitlearn" },
    { "name": "NLP", "icon": "SiOpenai" },
    { "name": "Docker", "icon": "SiDocker" },
    { "name": "Git", "icon": "SiGit" },
    { "name": "CI/CD", "icon": "SiGithubactions" },
    { "name": "AWS", "icon": "SiAmazonaws" },
    { "name": "Figma", "icon": "SiFigma" },
    { "name": "Responsive Design", "icon": "SiHtml5" },
    { "name": "Accessibility", "icon": "SiW3C" },
    { "name": "UI/UX", "icon": "SiAdobe" }
  ]
}
